Metadata-Version: 1.0
Name: bbcu.reportIlluminaInterop
Version: 1.0.3
Summary: Create SAV statistics. Run in python 2.7
Home-page: UNKNOWN
Author: Refael Kohen
Author-email: refael.kohen@gmail.com
License: UNKNOWN
Platform: UNKNOWN
